sc_utility/__init__.py
sc_utility/sc_common.py
sc_utility/sc_config_mgr.py
sc_utility/sc_csv_reader.py
sc_utility/sc_date_helper.py
sc_utility/sc_excel_reader.py
sc_utility/sc_json_encoder.py
sc_utility/sc_logging.py
sc_utility/sc_shelly_control.py
sc_utility/shelly_models.json
sc_utility/validation_schema.py
sc_utility/webhook_server.py
sc_utility-2.4.14.dist-info/licenses/LICENSE
weather_client/__init__.py
weather_client/client.py
weather_client/models.py
weather_client/providers/__init__.py
weather_client/providers/open_meteo_provider.py
weather_client/providers/owm_provider.py
sc_utility-2.4.14.dist-info/METADATA
sc_utility-2.4.14.dist-info/WHEEL
sc_utility-2.4.14.dist-info/top_level.txt
sc_utility-2.4.14.dist-info/RECORD
